{"chunk_definitions":[{"chunk_id":"c5kkfy663rfv9","chunk_label":"unnamed-chunk-1","document_id":"AC441C5D","expansion_state":0,"options":{"engine":"r","label":"unnamed-chunk-631"},"row":127,"row_count":1,"visible":true},{"chunk_id":"c4vw6yye6ach0","chunk_label":"unnamed-chunk-2","document_id":"AC441C5D","expansion_state":0,"options":{"engine":"r","label":"unnamed-chunk-632"},"row":163,"row_count":1,"visible":true},{"chunk_id":"c90wgtf9wu6w8","chunk_label":"unnamed-chunk-3","document_id":"AC441C5D","expansion_state":0,"options":{"engine":"r","label":"unnamed-chunk-633"},"row":196,"row_count":1,"visible":true},{"chunk_id":"cizqh8xu2567c","chunk_label":"unnamed-chunk-4","document_id":"AC441C5D","expansion_state":0,"options":{"engine":"r","label":"unnamed-chunk-634"},"row":206,"row_count":1,"visible":true},{"chunk_id":"cf2dfex2vnjy0","chunk_label":"unnamed-chunk-5","document_id":"AC441C5D","expansion_state":0,"options":{"engine":"r","label":"unnamed-chunk-635"},"row":217,"row_count":1,"visible":true},{"chunk_id":"ck0siqyvct934","chunk_label":"unnamed-chunk-6","document_id":"AC441C5D","expansion_state":0,"options":{"engine":"r","label":"unnamed-chunk-646"},"row":237,"row_count":1,"visible":true},{"chunk_id":"ceex91ambrc9j","chunk_label":"unnamed-chunk-7","document_id":"AC441C5D","expansion_state":0,"options":{"engine":"r","label":"unnamed-chunk-640"},"row":245,"row_count":1,"visible":true}],"chunk_rendered_width":700,"doc_write_time":1580531179}